chemotion_api/__init__.py
chemotion_api/__main__.py
chemotion_api/admin/__init__.py
chemotion_api/collection.py
chemotion_api/commands/__init__.py
chemotion_api/commands/creator.py
chemotion_api/commands/templates/productive/.env
chemotion_api/commands/templates/productive/docker-compose.yml
chemotion_api/commands/templates/productive/services/converter/htpasswd
chemotion_api/commands/templates/productive/shared/pullin/.version
chemotion_api/commands/templates/productive/shared/pullin/config/converter.yml
chemotion_api/commands/templates/productive/shared/pullin/config/shrine.yml
chemotion_api/commands/templates/productive/shared/pullin/config/spectra.yml
chemotion_api/commands/templates/productive/shared/pullin/db/seeds/json/dataset_klasses.json
chemotion_api/commands/updater.py
chemotion_api/connection.py
chemotion_api/converter/__init__.py
chemotion_api/element_manager.py
chemotion_api/elements/__init__.py
chemotion_api/elements/abstract_element.py
chemotion_api/elements/analyses_manager.py
chemotion_api/elements/attachments.py
chemotion_api/elements/empty_elements/__init__.py
chemotion_api/elements/empty_elements/analyses.json
chemotion_api/elements/empty_elements/container.json
chemotion_api/elements/empty_elements/dataset.json
chemotion_api/elements/empty_elements/reaction.json
chemotion_api/elements/empty_elements/research_plan.json
chemotion_api/elements/empty_elements/sample.json
chemotion_api/elements/empty_elements/sample_v2.json
chemotion_api/elements/empty_elements/solvents.json
chemotion_api/elements/empty_elements/wellplate.json
chemotion_api/elements/generic_element.py
chemotion_api/elements/reaction.py
chemotion_api/elements/research_plan.py
chemotion_api/elements/sample.py
chemotion_api/elements/schemas/reaction.py
chemotion_api/elements/schemas/research_plan.py
chemotion_api/elements/utils/__init__.py
chemotion_api/elements/utils/converter.py
chemotion_api/elements/utils/equivalent.py
chemotion_api/elements/wellplate.py
chemotion_api-0.300.7.dist-info/LICENSE
chemotion_api-0.300.7.dist-info/METADATA
chemotion_api-0.300.7.dist-info/WHEEL
chemotion_api-0.300.7.dist-info/entry_points.txt
chemotion_api-0.300.7.dist-info/RECORD
