Metadata-Version: 2.3
Name: chemotion-api
Version: 0.300.7
Summary: A Chemotion python API
License: MIT
Author: Maritn Starman
Author-email: martin.starman@kit.edu
Requires-Python: >=3.11,<4.0
Classifier: License :: OSI Approved :: MIT License
Classifier: Programming Language :: Python :: 3
Classifier: Programming Language :: Python :: 3.11
Classifier: Programming Language :: Python :: 3.12
Classifier: Programming Language :: Python :: 3.13
Requires-Dist: click (>=8.3.1,<9.0.0)
Requires-Dist: jinja2 (>=3.1.6,<4.0.0)
Requires-Dist: jsonschema (>=4.25.1,<5.0.0)
Requires-Dist: poetry-core (>=2.2.1,<3.0.0)
Requires-Dist: python-dateutil (>=2.9.0,<3.0.0)
Requires-Dist: python-magic (>=0.4.27,<0.5.0)
Requires-Dist: pytz (>=2025.2,<2026.0)
Requires-Dist: pyyaml (>=6.0.3,<7.0.0)
Requires-Dist: rdflib (>=7.5.0,<8.0.0)
Requires-Dist: requests (>=2.32.5,<3.0.0)
Requires-Dist: typing-extensions (>=4.15.0,<5.0.0)
